{"version":1,"resource":"file:///home/vladimir/BOTAY%21/Computational_mathematics_second_sem/hw3/%D0%97%D0%B0%D0%B4%D0%B0%D0%BD%D0%B8%D0%B5_3_%D0%A7%D0%B8%D1%81%D0%BB%D0%B5%D0%BD%D0%BD%D0%BE%D0%B5_%D0%98%D0%BD%D1%82%D0%B5%D0%B3%D1%80%D0%B8%D1%80%D0%BE%D0%B2%D0%B0%D0%BD%D0%B8%D0%B5.ipynb","entries":[{"id":"FVx8.ipynb","source":"edit","timestamp":1710505781703},{"id":"esNr.ipynb","source":"Update Cell Metadata","timestamp":1710505861715},{"id":"2ocu.ipynb","source":"edit","timestamp":1710506027580},{"id":"zDL6.ipynb","source":"Update Cell Metadata","timestamp":1710506061695},{"id":"xLmz.ipynb","source":"edit","timestamp":1710506113083},{"id":"dZJJ.ipynb","source":"Update Cell Metadata","timestamp":1710506135853},{"id":"xiV6.ipynb","source":"edit","timestamp":1710506147970},{"id":"BZGb.ipynb","source":"Update Cell Metadata","timestamp":1710506153988},{"id":"Tczn.ipynb","source":"edit","timestamp":1710506198382},{"id":"7pkp.ipynb","source":"Update Cell Metadata","timestamp":1710506205700},{"id":"p4JS.ipynb","source":"edit","timestamp":1710506252147},{"id":"C90D.ipynb","source":"Update Cell Metadata","timestamp":1710506264856},{"id":"9BXm.ipynb","source":"edit","timestamp":1710506269953},{"id":"hsmZ.ipynb","source":"Update Cell Metadata","timestamp":1710506275548},{"id":"rgI5.ipynb","source":"edit","timestamp":1710506285798},{"id":"HDCU.ipynb","source":"Update Cell Metadata","timestamp":1710506288661},{"id":"rwuX.ipynb","source":"edit","timestamp":1710506295919},{"id":"ZWa9.ipynb","source":"Update Cell Metadata","timestamp":1710506299727},{"id":"hTP9.ipynb","source":"edit","timestamp":1710506363995},{"id":"jes5.ipynb","source":"Update Cell Metadata","timestamp":1710506379950},{"id":"sewO.ipynb","source":"edit","timestamp":1710506392121},{"id":"0olh.ipynb","source":"Update Cell Metadata","timestamp":1710506396631},{"id":"khab.ipynb","source":"edit","timestamp":1710506446097},{"id":"JVwT.ipynb","source":"Update Cell Metadata","timestamp":1710506457725},{"id":"fFA9.ipynb","source":"edit","timestamp":1710506585428},{"id":"lE8T.ipynb","source":"Update Cell Metadata","timestamp":1710506595582},{"id":"lmlL.ipynb","source":"edit","timestamp":1710506597678},{"id":"G7Tc.ipynb","source":"Update Cell Metadata","timestamp":1710506607704},{"id":"eAOO.ipynb","timestamp":1710506712763},{"id":"L677.ipynb","timestamp":1710506760551},{"id":"8iRB.ipynb","timestamp":1710506779353},{"id":"C1JH.ipynb","source":"edit","timestamp":1710507020874},{"id":"hsf7.ipynb","source":"Update Cell Metadata","timestamp":1710507481467},{"id":"Dxzm.ipynb","source":"edit","timestamp":1710507557254},{"id":"fRYW.ipynb","source":"Update Cell Metadata","timestamp":1710507576486},{"id":"XQUb.ipynb","source":"edit","timestamp":1710507610526},{"id":"AF9l.ipynb","source":"Update Cell Metadata","timestamp":1710507614738},{"id":"i32l.ipynb","source":"edit","timestamp":1710507676428},{"id":"n1hT.ipynb","source":"Update Cell Metadata","timestamp":1710507684456},{"id":"lf7T.ipynb","source":"edit","timestamp":1710507729749},{"id":"fHV6.ipynb","source":"Update Cell Metadata","timestamp":1710507913389},{"id":"66qV.ipynb","source":"edit","timestamp":1710508444790},{"id":"PjaP.ipynb","source":"Update Cell Metadata","timestamp":1710508448533},{"id":"IlyF.ipynb","source":"edit","timestamp":1710509492660},{"id":"IOOG.ipynb","source":"edit","timestamp":1710540437069},{"id":"lH0i.ipynb","source":"Update Cell Metadata","timestamp":1710540456231},{"id":"Fr9A.ipynb","source":"edit","timestamp":1710540508668},{"id":"0LGb.ipynb","source":"Update Cell Metadata","timestamp":1710540552180},{"id":"4WPS.ipynb","source":"edit","timestamp":1710540579168},{"id":"yZp5.ipynb","source":"edit","timestamp":1710545055194}]}